arneso_pypitemplate_instance_uv/__init__.py
arneso_pypitemplate_instance_uv/__main__.py
arneso_pypitemplate_instance_uv/functions.py
arneso_pypitemplate_instance_uv/py.typed
arneso_pypitemplate_instance_uv-0.3.1.dist-info/WHEEL
arneso_pypitemplate_instance_uv-0.3.1.dist-info/entry_points.txt
arneso_pypitemplate_instance_uv-0.3.1.dist-info/METADATA
arneso_pypitemplate_instance_uv-0.3.1.dist-info/RECORD
