Metadata-Version: 2.4
Name: arneso-pypitemplate-instance-uv
Version: 0.3.1
Summary: Arneso Pypitemplate Instance Uv
Author: Arne Sørli
Author-email: Arne Sørli <arne.sorli@ssb.no>
License-Expression: MIT
Classifier: Programming Language :: Python :: 3
Classifier: Programming Language :: Python :: 3.10
Classifier: Programming Language :: Python :: 3.11
Classifier: Programming Language :: Python :: 3.12
Classifier: Programming Language :: Python :: 3.13
Classifier: License :: OSI Approved :: MIT License
Classifier: Development Status :: 4 - Beta
Classifier: Typing :: Typed
Requires-Dist: click>=8.0.1
Maintainer: Statistics Norway, IT-partner Department (703)
Requires-Python: >=3.10, <4.0
Project-URL: Changelog, https://github.com/arneso-ssb/arneso-pypitemplate-instance-uv/releases
Project-URL: documentation, https://arneso-ssb.github.io/arneso-pypitemplate-instance-uv
Project-URL: homepage, https://github.com/arneso-ssb/arneso-pypitemplate-instance-uv
Project-URL: repository, https://github.com/arneso-ssb/arneso-pypitemplate-instance-uv
